cse_code/__init__.py
cse_code/exp.py
cse_code-2.0.dist-info/METADATA
cse_code-2.0.dist-info/WHEEL
cse_code-2.0.dist-info/top_level.txt
cse_code-2.0.dist-info/RECORD
