Metadata-Version: 2.4
Name: cse_code
Version: 2.0
Summary: A CSE package
Author: naveenthegreat
Classifier: Programming Language :: Python :: 3
Dynamic: author
Dynamic: classifier
Dynamic: summary
